LICENSE
README.md
setup.py
metasequoia_connector/__init__.py
metasequoia_connector.egg-info/PKG-INFO
metasequoia_connector.egg-info/SOURCES.txt
metasequoia_connector.egg-info/dependency_links.txt
metasequoia_connector.egg-info/requires.txt
metasequoia_connector.egg-info/top_level.txt
metasequoia_connector/connector/__init__.py
metasequoia_connector/connector/common.py
metasequoia_connector/connector/ds_meta.py
metasequoia_connector/connector/hive.py
metasequoia_connector/connector/kafka.py
metasequoia_connector/connector/mysql.py
metasequoia_connector/connector/ots.py
metasequoia_connector/connector/redis.py
metasequoia_connector/connector/ssh_tunnel.py
metasequoia_connector/manager/__init__.py
metasequoia_connector/manager/connect_manager.py
metasequoia_connector/node/__init__.py
metasequoia_connector/node/combine.py
metasequoia_connector/node/common.py
metasequoia_connector/node/ds_meta.py
metasequoia_connector/node/hive.py
metasequoia_connector/node/kafka.py
metasequoia_connector/node/mysql.py
metasequoia_connector/node/ots.py
metasequoia_connector/node/redis.py
metasequoia_connector/node/ssh_tunnel.py
metasequoia_connector/utils/__init__.py
metasequoia_connector/utils/dolphin.py
metasequoia_connector/utils/hive.py
metasequoia_connector/utils/kafka.py
metasequoia_connector/utils/mysql.py
metasequoia_connector/utils/otssql.py
metasequoia_connector/utils/sql_format.py