Metadata-Version: 2.4
Name: metasequoia-connector
Version: 0.0.7
Summary: 水杉工具箱：数据库连接器
Home-page: 
Author: changxing
Author-email: 1278729001@qq.com
License: MIT License
Platform: all
Classifier: Intended Audience :: Developers
Classifier: Operating System :: OS Independent
Classifier: Natural Language :: Chinese (Simplified)
Classifier: Programming Language :: Python
Classifier: Programming Language :: Python :: 3.10
Classifier: Programming Language :: Python :: 3.11
Classifier: Programming Language :: Python :: 3.12
Classifier: Programming Language :: Python :: 3.13
Classifier: Topic :: Software Development :: Libraries
License-File: LICENSE
Requires-Dist: otssql
Requires-Dist: DBUtils
Requires-Dist: PyHive
Requires-Dist: PyMySQL
Requires-Dist: setuptools
Requires-Dist: sshtunnel
Requires-Dist: metasequoia_sql
Requires-Dist: kafka-python
Requires-Dist: redis
Requires-Dist: thrift
Dynamic: author
Dynamic: author-email
Dynamic: classifier
Dynamic: description
Dynamic: description-content-type
Dynamic: license
Dynamic: license-file
Dynamic: platform
Dynamic: requires-dist
Dynamic: summary
